MANIFEST.in
README.txt
setup.cfg
setup.py
docs/HISTORY.txt
docs/INSTALL.txt
docs/LICENSE.GPL
docs/LICENSE.txt
plonerules/.DS_Store
plonerules/__init__.py
plonerules/__init__.pyc
plonerules.slack.egg-info/PKG-INFO
plonerules.slack.egg-info/SOURCES.txt
plonerules.slack.egg-info/dependency_links.txt
plonerules.slack.egg-info/entry_points.txt
plonerules.slack.egg-info/namespace_packages.txt
plonerules.slack.egg-info/not-zip-safe
plonerules.slack.egg-info/paster_plugins.txt
plonerules.slack.egg-info/requires.txt
plonerules.slack.egg-info/top_level.txt
plonerules/slack/.DS_Store
plonerules/slack/__init__.py
plonerules/slack/__init__.pyc
plonerules/slack/configure.zcml
plonerules/slack/tests.py
plonerules/slack/actions/__init__.py
plonerules/slack/actions/__init__.pyc
plonerules/slack/actions/configure.zcml
plonerules/slack/actions/interfaces.py
plonerules/slack/actions/interfaces.pyc
plonerules/slack/actions/slack.py
plonerules/slack/actions/slack.pyc
plonerules/slack/profiles/.DS_Store
plonerules/slack/profiles/default/metadata.xml