Metadata-Version: 1.1
Name: plonerules.slack
Version: 1.0.3
Summary: Post to a slack channel action for plone rules
Home-page: https://github.com/sgiraud01/plonerules.slack/
Author: Steve Giraud
Author-email: sgiraud01@gmail.com
License: GPL
Keywords: slack plone rules
Platform: UNKNOWN
Classifier: Framework :: Plone
Classifier: Programming Language :: Python
